websocketd/__init__.py
websocketd/__main__.py
websocketd/builders.js
websocketd/rpc.js
websocket_httpd-0.5.dist-info/METADATA
websocket_httpd-0.5.dist-info/WHEEL
websocket_httpd-0.5.dist-info/copyright
websocket_httpd-0.5.dist-info/top_level.txt
websocket_httpd-0.5.dist-info/RECORD
