Metadata-Version: 2.1
Name: websocket-httpd
Version: 0.5
Summary: module for creating a http server which uses WebSockets
Home-page: https://github.com/wijnen/python-websocketd
Author: Bas Wijnen
Author-email: wijnen@debian.org
License: AGPL3+
Project-URL: Bug Tracker, https://github.com/wijnen/python-websocketd/issues
Classifier: Programming Language :: Python :: 3
Classifier: License :: OSI Approved :: GNU Affero General Public License v3 or later (AGPLv3+)
Classifier: Intended Audience :: Developers
Classifier: Development Status :: 4 - Beta
Classifier: Operating System :: OS Independent
Classifier: Topic :: System :: Networking
Classifier: Topic :: Internet :: WWW/HTTP :: HTTP Servers
Requires-Python: >=3
License-File: debian/copyright
Requires-Dist: fhs-paths
Requires-Dist: network-wrapper
